blacksheepcli/__init__.py
blacksheepcli/cli/__init__.py
blacksheepcli/cli/main.py
blacksheepcli/cli/py.typed
blacksheepcli/common/__init__.py
blacksheepcli/common/cookiemod.py
blacksheepcli/common/prompts.py
blacksheepcli/create/__init__.py
blacksheepcli/create/cli.py
blacksheepcli/create/domain.py
blacksheepcli/create/py.typed
blacksheepcli/templates/__init__.py
blacksheepcli/templates/cli.py
blacksheepcli/templates/domain.py
blacksheepcli/templates/py.typed
blacksheepcli/templates/data/__init__.py
blacksheepcli/templates/data/default.py
blacksheep_cli-0.0.5.dist-info/METADATA
blacksheep_cli-0.0.5.dist-info/WHEEL
blacksheep_cli-0.0.5.dist-info/entry_points.txt
blacksheep_cli-0.0.5.dist-info/licenses/LICENSE
blacksheep_cli-0.0.5.dist-info/RECORD
