Metadata-Version: 2.4
Name: blacksheep-cli
Version: 0.0.5
Summary: 🛠️ CLI to bootstrap BlackSheep projects
Project-URL: Homepage, https://github.com/Neoteroi/BlackSheep-CLI
Project-URL: Bug Tracker, https://github.com/Neoteroi/BlackSheep-CLI/issues
Author-email: Roberto Prevato <roberto.prevato@gmail.com>
License: MIT License
License-File: LICENSE
Keywords: CLI,blacksheep,developer experience,project templates,projects scaffolding
Classifier: Development Status :: 5 - Production/Stable
Classifier: Operating System :: OS Independent
Classifier: Programming Language :: Python :: 3
Classifier: Programming Language :: Python :: 3.8
Classifier: Programming Language :: Python :: 3.9
Classifier: Programming Language :: Python :: 3.10
Classifier: Programming Language :: Python :: 3.11
Classifier: Programming Language :: Python :: 3.12
Classifier: Programming Language :: Python :: 3.13
Requires-Python: >=3.7
Requires-Dist: click
Requires-Dist: cookiecutter
Requires-Dist: essentials-configuration[full]
Requires-Dist: pathvalidate
Requires-Dist: python-dotenv~=1.0.0
Requires-Dist: questionary
Requires-Dist: rich-click
Requires-Dist: tomli; python_version < '3.11'
